cloc/__init__.py
cloc/__main__.py
cloc/languages.json
plazma_cloc-1.2.4.dist-info/licenses/LICENSE
plazma_cloc-1.2.4.dist-info/METADATA
plazma_cloc-1.2.4.dist-info/WHEEL
plazma_cloc-1.2.4.dist-info/top_level.txt
plazma_cloc-1.2.4.dist-info/RECORD
