Metadata-Version: 2.4
Name: plazma-cloc
Version: 1.2.4
Summary: cloc (Count LOC) is a terminal utility to easily count lines of code in a file / project.
Author-email: CaptainDeathead <unstableplazma@gmail.com>
License: MIT License
Project-URL: Homepage, https://github.com/CaptainDeathead/cloc
Keywords: Command Line,CLI,Tool,Code,Utility,LOC
Classifier: License :: OSI Approved :: MIT License
Classifier: Programming Language :: Python
Classifier: Programming Language :: Python :: 3
Requires-Python: >3
License-File: LICENSE
Provides-Extra: dev
Dynamic: license-file
